{
    "name": "Access Token Invalidate",
    "domain": "https://api.loginradius.com",
    "path": "/api/v2/access_token/invalidate",
    "method": "GET",
    "getparams": {
        "key*": "@apikey@",
        "secret*": "@secret@",
        "access_token*": ""
    },
    "postparams": "",
    "headers": {
        "content-Type": "application/x-www-form-urlencoded"
    },
    "response": "json",
    "description": "This api invalidates the active access token.",
    "parameters": {
        "Get Params": [
            {
                "name": "api_key",
                "is_required": true,
                "description": "LoginRadius API Key"
            },
            {
                "name": "api_secret",
                "is_required": true,
                "description": "LoginRadius API Secret"
            },
            {
                "name": "access_token",
                "is_required": true,
                "description": "LoginRadius Access Token"
            }
        ]
    },
    "outputFormat": {
      "isPosted": true
        }
    }